LICENSE
MANIFEST.in
README.rst
setup.cfg
setup.py
django_webp_converter.egg-info/PKG-INFO
django_webp_converter.egg-info/SOURCES.txt
django_webp_converter.egg-info/dependency_links.txt
django_webp_converter.egg-info/requires.txt
django_webp_converter.egg-info/top_level.txt
webp_converter/__init__.py
webp_converter/context_processors.py
webp_converter/models.py
webp_converter/utils.py
webp_converter/conf/__init__.py
webp_converter/conf/settings.py
webp_converter/management/__init__.py
webp_converter/management/commands/__init__.py
webp_converter/management/commands/clear_webp_cache.py
webp_converter/migrations/0001_initial.py
webp_converter/migrations/0002_auto_20191202_1616.py
webp_converter/migrations/0003_auto_20191202_1621.py
webp_converter/migrations/__init__.py
webp_converter/templatetags/__init__.py
webp_converter/templatetags/webp_converter.py